LICENSE
README.md
setup.py
pyrotestlib/__init__.py
pyrotestlib/app.py
pyrotestlib.egg-info/PKG-INFO
pyrotestlib.egg-info/SOURCES.txt
pyrotestlib.egg-info/dependency_links.txt
pyrotestlib.egg-info/requires.txt
pyrotestlib.egg-info/top_level.txt